rustcord/__init__.py
rustcord/_rust.py
rustcord/client.py
rustcord/embeds.py
rustcord/errors.py
rustcord/gateway.py
rustcord/models.py
rustcord-0.1.4.dist-info/LICENSE
rustcord-0.1.4.dist-info/METADATA
rustcord-0.1.4.dist-info/WHEEL
rustcord-0.1.4.dist-info/top_level.txt
rustcord-0.1.4.dist-info/RECORD
