Metadata-Version: 2.1
Name: rustcord
Version: 0.1.4
Summary: A high-performance Discord API library with Rust core
Author-email: ghulq <ghulq@mcbehub.de>
License: MIT
Project-URL: Homepage, https://github.com/ghulq/rustcord
Project-URL: Bug Tracker, https://github.com/ghulq/rustcord/issues
Project-URL: Documentation, https://github.com/ghulq/rustcord#readme
Project-URL: Source, https://github.com/ghulq/rustcord
Keywords: discord,bot,api,rust,async,websocket,gateway
Classifier: Development Status :: 3 - Alpha
Classifier: Intended Audience :: Developers
Classifier: Topic :: Software Development :: Libraries :: Python Modules
Classifier: License :: OSI Approved :: MIT License
Classifier: Programming Language :: Python :: 3
Classifier: Programming Language :: Python :: 3.9
Classifier: Programming Language :: Python :: 3.10
Classifier: Programming Language :: Python :: 3.11
Classifier: Programming Language :: Python :: 3.12
Classifier: Programming Language :: Python :: 3.13
Classifier: Programming Language :: Rust
Classifier: Operating System :: OS Independent
Requires-Python: >=3.9
License-File: LICENSE
Requires-Dist: aiohttp >=3.11.0
Requires-Dist: websockets >=10.0
